{
  "project_info": {
    "project_number": "945693826861",
    "project_id": "eshop-app-5d35c",
    "storage_bucket": "eshop-app-5d35c.appspot.com"
  },
  "client": [
    {
      "client_info": {
        "mobilesdk_app_id": "1:945693826861:android:eacc15e947f12bac407da4",
        "android_client_info": {
          "package_name": "com.example.e_store"
        }
      },
      "oauth_client": [
        {
          "client_id": "945693826861-ggnkf7q5u67o9olld1022ufdi30981ch.apps.googleusercontent.com",
          "client_type": 3
        }
      ],
      "api_key": [
        {
          "current_key": "AIzaSyDlb1Ba8iX6e4zcPkx3SHYeWxSi4x6RL3k"
        }
      ],
      "services": {
        "appinvite_service": {
          "other_platform_oauth_client": [
            {
              "client_id": "945693826861-ggnkf7q5u67o9olld1022ufdi30981ch.apps.googleusercontent.com",
              "client_type": 3
            }
          ]
        }
      }
    }
  ],
  "configuration_version": "1"
}